cool_ascii/cli.py
cool_ascii-1.0.0.dist-info/METADATA
cool_ascii-1.0.0.dist-info/WHEEL
cool_ascii-1.0.0.dist-info/entry_points.txt
cool_ascii-1.0.0.dist-info/top_level.txt
cool_ascii-1.0.0.dist-info/RECORD
