Metadata-Version: 2.4
Name: cool-ascii
Version: 1.0.0
Summary: Cool ASCII menu CLI
Requires-Python: >=3.8
Requires-Dist: pyfiglet
Requires-Dist: termcolor
